.
.DS_Store
.editorconfig
.gitignore
.travis.yml
.travis.yml~
README.rst
setup.py
test.py
.github/ISSUE_TEMPLATE.md
cinemaPy.egg-info/PKG-INFO
cinemaPy.egg-info/SOURCES.txt
cinemaPy.egg-info/dependency_links.txt
cinemaPy.egg-info/requires.txt
cinemaPy.egg-info/top_level.txt
test/test.py