Metadata-Version: 1.0
Name: cinemaPy
Version: 0.1.0
Summary: Watch streaming movies
Home-page: UNKNOWN
Author: UNKNOWN
Author-email: UNKNOWN
License: MIT
Platform: UNKNOWN
